Workbook

Sheet 00_使用说明
A1: Tasman Naturals NZ — Pharma OEM Inventory Dashboard / v1.0
A2: A 3-tier inventory analytics tool for pharma OEM, covering raw materials, WIP, and finished goods, with batch traceability and expiry-driven loss prevention.
A4: 工具背景
A5: 适用场景：新西兰保健品 OEM (健康膳食补充剂合同制造)
A6: 核心问题：保健品行业 12-24 个月 shelf life，临期损耗是最大隐形成本
A7: 设计原则
A8: ① 三层立体库存监控 (Raw → WIP → FG)
A9: ② 90/60/30 天三级临期预警
A10: ③ 完整批次追溯链 (Raw Lot → WIP Batch → FG Batch → Customer Order)
A11: KPI 指标体系
A12: 1. Days on Hand (DOH) - 库存周转天数 → 衡量资金占用
A13: 2. Stock Coverage - 库存覆盖天数 → 衡量缺货风险
... A26: Step 7: 「07_Dashboard」给老板看的高管视图

Sheet 01_SKU档案
A1: SKU 主数据档案 (SKU Master)
A2: 所有产品 SKU 的主数据 — 是其他 sheet 的"查找表"
A4: SKU 编号 | B4: 产品名称 | C4: 剂型 | D4: 包装规格 | E4: 客户/品牌 | F4: 出口市场 | G4: 单位成本 (NZD) | H4: 单位售价 (NZD) | I4: Shelf Life (月) | J4: 最小起订量 (MOQ) | K4: Lead Time (天)
A5: TN-SG-001 | B5: Omega-3 1000mg Softgel | C5: 软胶囊 | D5: 120 caps/bottle | E5: KiwiHealth SEA | F5: Southeast Asia | G5: 0.18 | H5: 0.55 | I5: 24 | J5: 5000 | K5: 35
A6: TN-SG-002 | B6: Omega-3 Premium 1500mg | C6: 软胶囊 | D6: 120 caps/bottle | E6: PureLife AU | F6: Australia | G6: 0.28 | H6: 0.85 | I6: 24 | J6: 5000 | K6: 35
A7: TN-SG-003 | B7: Krill Oil 500mg Softgel | C7: 软胶囊 | D7: 60 caps/bottle | E7: KiwiHealth SEA | F7: Southeast Asia | G7: 0.42 | H7: 1.2 | I7: 24 | J7: 3000 | K7: 45
A8: TN-SG-004 | B8: CoQ10 100mg Softgel | C8: 软胶囊 | D8: 60 caps/bottle | E8: Bright Future CN | F8: China | G8: 0.32 | H8: 0.95 | I8: 24 | J8: 3000 | K8: 42
A9: TN-SG-005 | B9: CoQ10 Ubiquinol Premium | C9: 软胶囊 | D9: 120 caps/bottle | E9: VitalPath US | F9: USA | G9: 0.55 | H9: 1.65 | I9: 24 | J9: 3000 | K9: 42
A10: TN-SG-006 | B10: Vitamin D3 1000IU Softgel | C10: 软胶囊 | D10: 60 caps/bottle | E10: Bright Future CN | F10: China | G10: 0.08 | H10: 0.28 | I10: 36 | J10: 10000 | K10: 28
A11: TN-SG-007 | B11: Vitamin D3 5000IU Softgel | C11: 软胶囊 | D11: 30 caps/bottle | E11: KiwiHealth SEA | F11: Southeast Asia | G11: 0.12 | H11: 0.42 | I11: 36 | J11: 10000 | K11: 28
A12: TN-SG-008 | B12: Vitamin E 400IU Softgel | C12: 软胶囊 | D12: 120 caps/bottle | E12: PureLife AU | F12: Australia | G12: 0.09 | H12: 0.32 | I12: 24 | J12: 8000 | K12: 30
A13: TN-SG-009 | B13: Fish Oil + Vitamin D3 Combo | C13: 软胶囊 | D13: 30 caps/bottle | E13: Bright Future CN | F13: China | G13: 0.21 | H13: 0.68 | I13: 24 | J13: 5000 | K13: 38
A14: TN-SG-010 | B14: Shark Liver Oil Softgel | C14: 软胶囊 | D14: 30 caps/bottle | E14: Bright Future CN | F14: China | G14: 0.38 | H14: 1.1 | I14: 24 | J14: 3000 | K14: 40
A15: TN-SG-011 | B15: Evening Primrose Oil | C15: 软胶囊 | D15: 60 caps/bottle | E15: PureLife AU | F15: Australia | G15: 0.15 | H15: 0.48 | I15: 24 | J15: 6000 | K15: 32
A16: TN-SG-012 | B16: Borage Oil 1000mg | C16: 软胶囊 | D16: 30 caps/bottle | E16: KiwiHealth SEA | F16: Southeast Asia | G16: 0.22 | H16: 0.72 | I16: 24 | J16: 5000 | K16: 32
... A84: TN-PW-016 | B84: Beetroot Powder Natural 200g | C84: 粉剂 | D84: 200g jar | E84: PureLife AU | F84: Australia | G84: 4.5 | H84: 13 | I84: 24 | J84: 1500 | K84: 35

Sheet 02_原料库存
A1: 原料层库存 (Raw Materials Inventory)
A2: 按 Lot 号管理 ：每个原料批次独立追踪效期
A4: 原料 Lot 号 | B4: 供应商编号 | C4: 供应商名称 | D4: 原料品类 | E4: 入库日期 | F4: 效期截止 | G4: 入库数量 (kg) | H4: 剩余数量 (kg) | I4: 单位成本 (NZD/kg) | J4: 状态
A5: LOT-P004-2605-018 | B5: P004 | C5: Westland Milk Proteins | D5: 原料-乳清分离蛋白WPI | E5: 46156 | F5: 46696 | G5: 50 | H5: 49.1 | I5: 110 | J5: 正常
A6: LOT-P010-2605-042 | B6: P010 | C6: Sirio Pharma | D6: 原料-葡萄糖胺 | E6: 46156 | F6: 46876 | G6: 800 | H6: 787.8 | I6: 180 | J6: 正常
A7: LOT-P011-2605-047 | B7: P011 | C7: SeaDragon Ltd | D7: 原料-鲨鱼肝油角鲨烯 | E7: 46156 | F7: 46876 | G7: 300 | H7: 295.7 | I7: 350 | J7: 正常
A8: LOT-P002-2605-006 | B8: P002 | C8: Pacific Krill Co | D8: 原料-磷虾油 | E8: 46155 | F8: 46875 | G8: 200 | H8: 196.8 | I8: 480 | J8: 正常
A9: LOT-P009-2605-039 | B9: P009 | C9: DSM Nutritional Products | D9: 原料-维生素D3 | E9: 46155 | F9: 47235 | G9: 1000 | H9: 992 | I9: 520 | J9: 正常
A10: LOT-P013-2605-056 | B10: P013 | C10: Tianjin Tianyao Pharma | D10: 原料-矿物质钙镁锌 | E10: 46150 | F10: 47230 | G10: 500 | H10: 495.4 | I10: 38 | J10: 正常
A11: LOT-P005-2604-022 | B11: P005 | C11: Comvita Manuka Honey | D11: 原料-麦卢卡蜂蜜 | E11: 46142 | F11: 46862 | G11: 1000 | H11: 968.6 | I11: 280 | J11: 正常
A12: LOT-P002-2604-009 | B12: P002 | C12: Pacific Krill Co | D12: 原料-磷虾油 | E12: 46138 | F12: 46858 | G12: 100 | H12: 95.6 | I12: 480 | J12: 正常
A13: LOT-P009-2604-041 | B13: P009 | C13: DSM Nutritional Products | D13: 原料-维生素D3 | E13: 46136 | F13: 47216 | G13: 300 | H13: 293.6 | I13: 520 | J13: 正常
A14: LOT-P003-2604-014 | B14: P003 | C14: Tatua Whey NZ | D14: 原料-乳清蛋白WPC | E14: 46135 | F14: 46675 | G14: 300 | H14: 283.7 | I14: 85 | J14: 正常
A15: LOT-P006-2604-025 | B15: P006 | C15: Shanghai BioChem Ltd | D15: 原料-维生素C | E15: 46132 | F15: 47212 | G15: 150 | H15: 144.4 | I15: 45 | J15: 正常
A16: LOT-P001-2604-003 | B16: P001 | C16: Omega Marine Oils Ltd | D16: 原料-Omega鱼油 | E16: 46130 | F16: 46850 | G16: 50 | H16: 48.2 | I16: 250 | J16: 正常
... A62: LOT-P006-2306-028 | B62: P006 | C62: Shanghai BioChem Ltd | D62: 原料-维生素C | E62: 45094 | F62: 46174 | G62: 200 | H62: 10 | I62: 45 | J62: 临期-红

Sheet 03_WIP在制品
A1: 在制品层库存 (Work-in-Process Inventory)
A2: 追踪正在生产中的批次 — 关联到原料 Lot 和成品 SKU
A4: WIP 批号 | B4: 目标 SKU | C4: 使用的原料 Lot | D4: 投料日期 | E4: 预计完工日 | F4: 投料数量 (kg) | G4: 预计产出 (单位数) | H4: 当前阶段 | I4: 状态
A5: WIP-2605-023 | B5: TN-SG-020 | C5: LOT-P001-2603-004 | D5: 46164 | E5: 46178 | F5: 10 | G5: 12670 | H5: 压片/灌装 | I5: 进行中
A6: WIP-2605-004 | B6: TN-SG-004 | C6: LOT-P007-2602-033 | D6: 46163 | E6: 46175 | F6: 100 | G6: 123700 | H6: QA检测 | I6: 进行中
A7: WIP-2605-018 | B7: TN-HG-006 | C7: LOT-P010-2602-044 | D7: 46163 | E7: 46174 | F7: 30 | G7: 40710 | H7: 包装 | I7: 即将完工
A8: WIP-2605-022 | B8: TN-SG-003 | C8: LOT-P002-2512-007 | D8: 46163 | E8: 46170 | F8: 20 | G8: 18980 | H8: 称料 | I8: 进行中
A9: WIP-2605-016 | B9: TN-SG-010 | C9: LOT-P011-2601-051 | D9: 46162 | E9: 46171 | F9: 100 | G9: 91500 | H9: 完工待转 | I9: 完工待转
A10: WIP-2605-027 | B10: TN-PW-003 | C10: LOT-P003-2601-013 | D10: 46162 | E10: 46173 | F10: 100 | G10: 141400 | H10: 称料 | I10: 进行中
A11: WIP-2605-017 | B11: TN-SG-003 | C11: LOT-P002-2603-011 | D11: 46161 | E11: 46169 | F11: 10 | G11: 8340 | H11: 完工待转 | I11: 完工待转
A12: WIP-2605-006 | B12: TN-PW-009 | C12: LOT-P005-2603-021 | D12: 46159 | E12: 46172 | F12: 30 | G12: 41670 | H12: QA检测 | I12: 进行中
A13: WIP-2605-025 | B13: TN-SG-003 | C13: LOT-P002-2604-009 | D13: 46159 | E13: 46168 | F13: 80 | G13: 118800 | H13: 称料 | I13: 进行中
A14: WIP-2605-029 | B14: TN-SG-001 | C14: LOT-P001-2603-004 | D14: 46158 | E14: 46171 | F14: 30 | G14: 27030 | H14: 完工待转 | I14: 完工待转
A15: WIP-2605-014 | B15: TN-SG-009 | C15: LOT-P001-2603-004 | D15: 46156 | E15: 46167 | F15: 50 | G15: 65250 | H15: 包装 | I15: 即将完工
A16: WIP-2605-021 | B16: TN-SG-003 | C16: LOT-P002-2605-006 | D16: 46156 | E16: 46163 | F16: 80 | G16: 95600 | H16: 称料 | I16: 已转成品
... A34: WIP-2604-028 | B34: TN-HG-006 | C34: LOT-P010-2512-043 | D34: 46140 | E34: 46149 | F34: 10 | G34: 13200 | H34: QA检测 | I34: 已转成品

Sheet 04_成品库存
A1: 成品层库存 (Finished Goods Inventory)
A2: 按生产批号管理 — 每个成品批次独立追踪效期到客户
A4: 成品批号 | B4: SKU 编号 | C4: 产品名称 | D4: 来源 WIP 批号 | E4: 生产日期 | F4: 效期截止 | G4: 入库数量 | H4: 当前数量 | I4: 库存价值 (NZD) | J4: 状态
A5: FG-SG-260522-023 | B5: TN-SG-002 | C5: Omega-3 Premium 1500mg | D5: WIP-LEGACY-900 | E5: 46164 | F5: 46884 | G5: 30000 | H5: 29962 | I5: 25468 | J5: 正常
A6: FG-SG-260522-031 | B6: TN-SG-007 | C6: Vitamin D3 5000IU Softgel | D6: WIP-2605-002 | E6: 46164 | F6: 47244 | G6: 3000 | H6: 2997 | I6: 1259 | J6: 正常
A7: FG-HG-260522-089 | B7: TN-HG-006 | C7: Glucosamine + Curcumin | D7: WIP-2605-018 | E7: 46164 | F7: 46884 | G7: 10000 | H7: 9989 | I7: 7791 | J7: 正常
A8: FG-SG-260522-118 | B8: TN-SG-020 | C8: Salmon Oil Wild Caught | D8: WIP-2605-023 | E8: 46164 | F8: 46884 | G8: 15000 | H8: 14989 | I8: 11691 | J8: 正常
A9: FG-PW-260520-097 | B9: TN-PW-002 | C9: WPI Whey Protein Chocolate 1kg | D9: WIP-LEGACY-347 | E9: 46162 | F9: 46702 | G9: 10000 | H9: 9955 | I9: 238920 | J9: 正常
A10: FG-SG-260519-018 | B10: TN-SG-003 | C10: Krill Oil 500mg Softgel | D10: WIP-2605-021 | E10: 46161 | F10: 46881 | G10: 8000 | H10: 7951 | I10: 9541 | J10: 正常
A11: FG-HG-260516-043 | B11: TN-HG-007 | C11: Ginseng Extract 500mg | D11: WIP-LEGACY-212 | E11: 46158 | F11: 46878 | G11: 15000 | H11: 14931 | I11: 8660 | J11: 正常
A12: FG-SG-260515-034 | B12: TN-SG-007 | C12: Vitamin D3 5000IU Softgel | D12: WIP-LEGACY-969 | E12: 46157 | F12: 47237 | G12: 3000 | H12: 2979 | I12: 1251 | J12: 正常
A13: FG-TB-260514-010 | B13: TN-TB-017 | C13: Heart Health CoQ10 Complex | D13: WIP-LEGACY-447 | E13: 46156 | F13: 46876 | G13: 20000 | H13: 19869 | I13: 20862 | J13: 正常
A14: FG-PW-260512-108 | B14: TN-PW-004 | C14: Whey Protein Berry 1kg | D14: WIP-LEGACY-456 | E14: 46154 | F14: 46694 | G14: 30000 | H14: 29461 | I14: 721794 | J14: 正常
A15: FG-SG-260511-052 | B15: TN-SG-003 | C15: Krill Oil 500mg Softgel | D15: WIP-LEGACY-671 | E15: 46153 | F15: 46873 | G15: 10000 | H15: 9888 | I15: 11866 | J15: 正常
A16: FG-PW-260511-054 | B16: TN-PW-004 | C16: Whey Protein Berry 1kg | D16: WIP-LEGACY-569 | E16: 46153 | F16: 46693 | G16: 8000 | H16: 7803 | I16: 191174 | J16: 正常
... A124: FG-TB-230419-012 | B124: TN-TB-004 | C124: Calcium + Magnesium + Zinc | D124: WIP-LEGACY-875 | E124: 45035 | F124: 46115 | G124: 30000 | H124: 15463 | I124: 5412 | J124: 过期

Sheet 05_临期预警
A1: 临期预警与损失估算 (Expiry Alert & Loss Estimation)
A2: 90/60/30 天三色预警 — 自动识别临期库存与潜在损失
A4: 批号 | B4: 类型 (原料/WIP/成品) | C4: SKU 编号 | D4: 效期截止 | E4: 剩余天数 | F4: 预警等级 | G4: 当前库存价值 (NZD) | H4: 处理建议
A5: {=_xlfn.LET(_xlpm.rawRange, '02_原料库存'!A5:J100, _xlpm.rawValid, _xlfn._xlws.FILTER(_xlpm.rawRange, (INDEX(_xlpm.rawRange,,10)<>"正常")*(INDEX(_xlpm.rawRange,,10)<>"已耗尽")*(INDEX(_xlpm.rawRange,,1)<>"")), _xlpm.rawOut, _xlfn.HSTACK(INDEX(_xlpm.rawValid,,1), IF(INDEX(_xlpm.rawValid,,1)<>"","原料",""), IF(INDEX(_xlpm.rawValid,,1)<>"","N/A",""), INDEX(_xlpm.rawValid,,6), INDEX(_xlpm.rawValid,,6)-TODAY(), INDEX(_xlpm.rawValid,,10), INDEX(_xlpm.rawValid,,8)*INDEX(_xlpm.rawValid,,9)), _xlpm.fgRange, '04_成品库存'!A5:J150, _xlpm.fgValid, _xlfn._xlws.FILTER(_xlpm.fgRange, (INDEX(_xlpm.fgRange,,10)<>"正常")*(INDEX(_xlpm.fgRange,,10)<>"已售罄")*(INDEX(_xlpm.fgRange,,1)<>"")), _xlpm.fgOut, _xlfn.HSTACK(INDEX(_xlpm.fgValid,,1), IF(INDEX(_xlpm.fgValid,,1)<>"","成品",""), INDEX(_xlpm.fgValid,,2), INDEX(_xlpm.fgValid,,6), INDEX(_xlpm.fgValid,,6)-TODAY(), INDEX(_xlpm.fgValid,,10), INDEX(_xlpm.fgValid,,9)), _xlpm.combined, _xlfn.VSTACK(_xlpm.rawOut, _xlpm.fgOut), _xlfn._xlws.SORT(_xlpm.combined, 5, 1))} -> FG-HG-240926-090 | B5: 成品 | C5: TN-HG-002 | D5: 46101 | E5: -64 | F5: 过期 | G5: 10103 | H5: =IF(A5="","",IF(F5="过期","🚨 立即报废 + 召回审计",IF(F5="临期-红","⚡ 7天内促销/退货",IF(F5="临期-橙","⚠️ 30天内对接销售折扣",IF(F5="临期-黄","📋 进入观察名单","正常"))))) -> 🚨 立即报废 + 召回审计
A6: FG-PW-241003-086 | B6: 成品 | C6: TN-PW-003 | D6: 46108 | E6: -57 | F6: 过期 | G6: 9500 | H6: =IF(A6="","",IF(F6="过期","🚨 立即报废 + 召回审计",IF(F6="临期-红","⚡ 7天内促销/退货",IF(F6="临期-橙","⚠️ 30天内对接销售折扣",IF(F6="临期-黄","📋 进入观察名单","正常"))))) -> 🚨 立即报废 + 召回审计
A7: FG-PW-241007-040 | B7: 成品 | C7: TN-PW-003 | D7: 46112 | E7: -53 | F7: 过期 | G7: 7600 | H7: =IF(A7="","",IF(F7="过期","🚨 立即报废 + 召回审计",IF(F7="临期-红","⚡ 7天内促销/退货",IF(F7="临期-橙","⚠️ 30天内对接销售折扣",IF(F7="临期-黄","📋 进入观察名单","正常"))))) -> 🚨 立即报废 + 召回审计
A8: FG-SG-240412-011 | B8: 成品 | C8: TN-SG-001 | D8: 46114 | E8: -51 | F8: 过期 | G8: 884 | H8: =IF(A8="","",IF(F8="过期","🚨 立即报废 + 召回审计",IF(F8="临期-红","⚡ 7天内促销/退货",IF(F8="临期-橙","⚠️ 30天内对接销售折扣",IF(F8="临期-黄","📋 进入观察名单","正常"))))) -> 🚨 立即报废 + 召回审计
A9: FG-TB-230419-012 | B9: 成品 | C9: TN-TB-004 | D9: 46115 | E9: -50 | F9: 过期 | G9: 5412 | H9: =IF(A9="","",IF(F9="过期","🚨 立即报废 + 召回审计",IF(F9="临期-红","⚡ 7天内促销/退货",IF(F9="临期-橙","⚠️ 30天内对接销售折扣",IF(F9="临期-黄","📋 进入观察名单","正常"))))) -> 🚨 立即报废 + 召回审计
A10: FG-SG-240417-075 | B10: 成品 | C10: TN-SG-010 | D10: 46119 | E10: -46 | F10: 过期 | G10: 4551 | H10: =IF(A10="","",IF(F10="过期","🚨 立即报废 + 召回审计",IF(F10="临期-红","⚡ 7天内促销/退货",IF(F10="临期-橙","⚠️ 30天内对接销售折扣",IF(F10="临期-黄","📋 进入观察名单","正常"))))) -> 🚨 立即报废 + 召回审计
A11: FG-SG-240426-065 | B11: 成品 | C11: TN-SG-020 | D11: 46128 | E11: -37 | F11: 过期 | G11: 312 | H11: =IF(A11="","",IF(F11="过期","🚨 立即报废 + 召回审计",IF(F11="临期-红","⚡ 7天内促销/退货",IF(F11="临期-橙","⚠️ 30天内对接销售折扣",IF(F11="临期-黄","📋 进入观察名单","正常"))))) -> 🚨 立即报废 + 召回审计
A12: FG-HG-241104-068 | B12: 成品 | C12: TN-HG-002 | D12: 46140 | E12: -25 | F12: 过期 | G12: 15097 | H12: =IF(A12="","",IF(F12="过期","🚨 立即报废 + 召回审计",IF(F12="临期-红","⚡ 7天内促销/退货",IF(F12="临期-橙","⚠️ 30天内对接销售折扣",IF(F12="临期-黄","📋 进入观察名单","正常"))))) -> 🚨 立即报废 + 召回审计
A13: LOT-P008-2505-037 | B13: 原料 | C13: N/A | D13: 46144 | E13: -21 | F13: 过期 | G13: 21750 | H13: =IF(A13="","",IF(F13="过期","🚨 立即报废 + 召回审计",IF(F13="临期-红","⚡ 7天内促销/退货",IF(F13="临期-橙","⚠️ 30天内对接销售折扣",IF(F13="临期-黄","📋 进入观察名单","正常"))))) -> 🚨 立即报废 + 召回审计
A14: LOT-P002-2405-008 | B14: 原料 | C14: N/A | D14: 46147 | E14: -18 | F14: 过期 | G14: 12000 | H14: =IF(A14="","",IF(F14="过期","🚨 立即报废 + 召回审计",IF(F14="临期-红","⚡ 7天内促销/退货",IF(F14="临期-橙","⚠️ 30天内对接销售折扣",IF(F14="临期-黄","📋 进入观察名单","正常"))))) -> 🚨 立即报废 + 召回审计
A15: FG-PW-240519-015 | B15: 成品 | C15: TN-PW-010 | D15: 46151 | E15: -14 | F15: 过期 | G15: 62140 | H15: =IF(A15="","",IF(F15="过期","🚨 立即报废 + 召回审计",IF(F15="临期-红","⚡ 7天内促销/退货",IF(F15="临期-橙","⚠️ 30天内对接销售折扣",IF(F15="临期-黄","📋 进入观察名单","正常"))))) -> 🚨 立即报废 + 召回审计
A16: LOT-P007-2405-034 | B16: 原料 | C16: N/A | D16: 46153 | E16: -12 | F16: 过期 | G16: 7350 | H16: =IF(A16="","",IF(F16="过期","🚨 立即报废 + 召回审计",IF(F16="临期-红","⚡ 7天内促销/退货",IF(F16="临期-橙","⚠️ 30天内对接销售折扣",IF(F16="临期-黄","📋 进入观察名单","正常"))))) -> 🚨 立即报废 + 召回审计
A17: FG-TB-230527-094 | B17: 成品 | C17: TN-TB-001 | D17: 46153 | E17: -12 | F17: 过期 | G17: 488 | H17: =IF(A17="","",IF(F17="过期","🚨 立即报废 + 召回审计",IF(F17="临期-红","⚡ 7天内促销/退货",IF(F17="临期-橙","⚠️ 30天内对接销售折扣",IF(F17="临期-黄","📋 进入观察名单","正常"))))) -> 🚨 立即报废 + 召回审计
... A61: FG-HG-240831-037 | B61: 成品 | C61: TN-HG-006 | D61: 46255 | E61: 90 | F61: 临期-黄 | G61: 1399 | H61: =IF(A61="","",IF(F61="过期","🚨 立即报废 + 召回审计",IF(F61="临期-红","⚡ 7天内促销/退货",IF(F61="临期-橙","⚠️ 30天内对接销售折扣",IF(F61="临期-黄","📋 进入观察名单","正常"))))) -> 📋 进入观察名单

Sheet 06_批次追溯
A1: 批次追溯演示 (Batch Traceability Showcase)
A2: 完整追溯链：原料 Lot → WIP 批号 → 成品批号 → 客户订单
A4: 追溯起点 | B4: 原料 Lot 号 | C4: WIP 批号 | D4: 成品批号 | E4: 客户订单号 | F4: 追溯响应时间

Sheet 07_Dashboard
A1: 高管视图 — Inventory Health Dashboard
A2: 关键指标一目了然：库存价值、临期预警、周转率、批次追溯演示
A4: SKU 总数 | C4: 原料 Lot 数 | E4: WIP 批次数 | G4: 成品批号数
A5: =COUNTA('01_SKU档案'!A5:A100) -> 80 | C5: =COUNTA('02_原料库存'!A5:A100) -> 58 | E5: =COUNTA('03_WIP在制品'!A5:A100) -> 30 | G5: =COUNTA('04_成品库存'!A5:A200) -> 120
A8: 总库存价值 (NZD) | C8: 已过期价值 | E8: 30 天临期价值 | G8: 60 天临期价值
A9: =SUMPRODUCT('02_原料库存'!H5:H100, '02_原料库存'!I5:I100) + SUM('04_成品库存'!I5:I200) -> 15018950 | C9: =SUMIF('05_临期预警'!F:F,"过期",'05_临期预警'!G:G) -> 200487 | E9: =SUMIF('05_临期预警'!F:F,"临期-红",'05_临期预警'!G:G) -> 350473 | G9: =SUMIF('05_临期预警'!F:F,"临期-橙",'05_临期预警'!G:G) -> 173614.5
A12: 图表数据源：按剂型分布 | J12: 图表数据源：按客户分布
A13: 剂型 | B13: SKU 数量 | J13: 客户 | K13: SKU 数量
A14: 软胶囊 | B14: =COUNTIF('01_SKU档案'!C:C,"软胶囊") -> 22 | J14: Bright Future CN | K14: =COUNTIF('01_SKU档案'!E:E,"Bright Future CN") -> 21
A15: 硬胶囊 | B15: =COUNTIF('01_SKU档案'!C:C,"硬胶囊") -> 24 | J15: PureLife AU | K15: =COUNTIF('01_SKU档案'!E:E,"PureLife AU") -> 24
A16: 片剂 | B16: =COUNTIF('01_SKU档案'!C:C,"片剂") -> 18 | J16: VitalPath US | K16: =COUNTIF('01_SKU档案'!E:E,"VitalPath US") -> 12
A17: 粉剂 | B17: =COUNTIF('01_SKU档案'!C:C,"粉剂") -> 16 | J17: KiwiHealth SEA | K17: =COUNTIF('01_SKU档案'!E:E,"KiwiHealth SEA") -> 23
A24: Top 10 高风险批次 (按剩余天数升序)
A25: 批号 | B25: 类型 | C25: SKU 编号 | D25: 效期截止 | E25: 剩余天数 | F25: 预警等级 | G25: 库存价值 (NZD) | H25: 处理建议
A26: {=_xlfn.TAKE('05_临期预警'!A5:H100,10)} -> FG-HG-240926-090 | B26: 成品 | C26: TN-HG-002 | D26: 46101 | E26: -64 | F26: 过期 | G26: 10103 | H26: 🚨 立即报废 + 召回审计
A27: FG-PW-241003-086 | B27: 成品 | C27: TN-PW-003 | D27: 46108 | E27: -57 | F27: 过期 | G27: 9500 | H27: 🚨 立即报废 + 召回审计
A28: FG-PW-241007-040 | B28: 成品 | C28: TN-PW-003 | D28: 46112 | E28: -53 | F28: 过期 | G28: 7600 | H28: 🚨 立即报废 + 召回审计
A29: FG-SG-240412-011 | B29: 成品 | C29: TN-SG-001 | D29: 46114 | E29: -51 | F29: 过期 | G29: 884 | H29: 🚨 立即报废 + 召回审计
A30: FG-TB-230419-012 | B30: 成品 | C30: TN-TB-004 | D30: 46115 | E30: -50 | F30: 过期 | G30: 5412 | H30: 🚨 立即报废 + 召回审计
A31: FG-SG-240417-075 | B31: 成品 | C31: TN-SG-010 | D31: 46119 | E31: -46 | F31: 过期 | G31: 4551 | H31: 🚨 立即报废 + 召回审计
A32: FG-SG-240426-065 | B32: 成品 | C32: TN-SG-020 | D32: 46128 | E32: -37 | F32: 过期 | G32: 312 | H32: 🚨 立即报废 + 召回审计
A33: FG-HG-241104-068 | B33: 成品 | C33: TN-HG-002 | D33: 46140 | E33: -25 | F33: 过期 | G33: 15097 | H33: 🚨 立即报废 + 召回审计
A34: LOT-P008-2505-037 | B34: 原料 | C34: N/A | D34: 46144 | E34: -21 | F34: 过期 | G34: 21750 | H34: 🚨 立即报废 + 召回审计
A35: LOT-P002-2405-008 | B35: 原料 | C35: N/A | D35: 46147 | E35: -18 | F35: 过期 | G35: 12000 | H35: 🚨 立即报废 + 召回审计
A38: 批次追溯演示 (Batch Traceability Showcase)
A39: 输入任意成品批号，自动追溯完整生产链
A41: 🔍 输入成品批号: | B41: FG-SG-260522-031
A43: 追溯环节 | B43: 标识符 | C43: 关键信息 | D43: 数量 | E43: 日期
A44: 成品 (FG) | B44: =B41 -> FG-SG-260522-031 | C44: =IFERROR(VLOOKUP(B41,'04_成品库存'!A:J,3,FALSE),"❌ 未找到此批号") -> Vitamin D3 5000IU Softgel | D44: =IFERROR(VLOOKUP(B41,'04_成品库存'!A:J,8,FALSE),"") -> 2997 | E44: =IFERROR(VLOOKUP(B41,'04_成品库存'!A:J,5,FALSE),"") -> 46164
A45: ← 来自 WIP 批号 | B45: =IFERROR(VLOOKUP(B41,'04_成品库存'!A:J,4,FALSE),"") -> WIP-2605-002 | C45: =IFERROR(VLOOKUP(B45,'03_WIP在制品'!A:I,8,FALSE),"(可能是历史批次)") -> QA检测 | D45: =IFERROR(VLOOKUP(B45,'03_WIP在制品'!A:I,7,FALSE),"") -> 13030 | E45: =IFERROR(VLOOKUP(B45,'03_WIP在制品'!A:I,4,FALSE),"") -> 46152
A46: ← 来自原料 Lot | B46: =IFERROR(VLOOKUP(B45,'03_WIP在制品'!A:I,3,FALSE),"") -> LOT-P009-2604-041 | C46: =IFERROR(VLOOKUP(B46,'02_原料库存'!A:J,3,FALSE)&" / "&VLOOKUP(B46,'02_原料库存'!A:J,4,FALSE),"") -> DSM Nutritional Products / 原料-维生素D3 | D46: =IFERROR(VLOOKUP(B46,'02_原料库存'!A:J,7,FALSE),"") -> 300 | E46: =IFERROR(VLOOKUP(B46,'02_原料库存'!A:J,5,FALSE),"") -> 46136
A48: 试试这些批号: FG-SG-260522-031 | FG-HG-260522-089 | FG-PW-260520-097
